enterdir/__init__.py
tests/__init__.py
enterdir-0.0.2.dist-info/LICENSE
enterdir-0.0.2.dist-info/METADATA
enterdir-0.0.2.dist-info/WHEEL
enterdir-0.0.2.dist-info/top_level.txt
enterdir-0.0.2.dist-info/RECORD
